track_UB_usage_XBT/__init__.py
track_UB_usage_XBT/main.py
track_UB_proxy_usage_XBT-0.1.3.dist-info/METADATA
track_UB_proxy_usage_XBT-0.1.3.dist-info/WHEEL
track_UB_proxy_usage_XBT-0.1.3.dist-info/top_level.txt
track_UB_proxy_usage_XBT-0.1.3.dist-info/RECORD
