Metadata-Version: 2.1
Name: track_UB_proxy_usage_XBT
Version: 0.1.3
Summary: A package to monitor third-party proxy usage
Author: Bhumika Bhatti
Author-email: bhumika.bhatti@xbyte.io
Classifier: Programming Language :: Python :: 3
Classifier: License :: OSI Approved :: MIT License
Classifier: Operating System :: OS Independent
Requires-Python: >=3.6
